ve_power_meter/__init__.py
ve_power_meter-0.1.0.dist-info/LICENSE
ve_power_meter-0.1.0.dist-info/METADATA
ve_power_meter-0.1.0.dist-info/WHEEL
ve_power_meter-0.1.0.dist-info/entry_points.txt
ve_power_meter-0.1.0.dist-info/top_level.txt
ve_power_meter-0.1.0.dist-info/RECORD
