Metadata-Version: 2.1
Name: ve-power-meter
Version: 0.1.0
Summary: Power meeasurement tool for the NEC Vector Engine
Home-page: http://github.com/keichi/ve-power-meter
Author: Keichi Takahashi
Author-email: hello@keichi.dev
License: MIT
License-File: LICENSE
